sparkit/__init__.py
sparkit/column.py
sparkit/frame.py
sparkit/parse.py
sparkit/render.py
sparkit/sql.py
sparkit/expression/__init__.py
sparkit/expression/base.py
sparkit/expression/clause.py
sparkit/expression/datatype.py
sparkit/expression/function.py
sparkit/expression/join.py
sparkit/expression/operator.py
sparkit/expression/query.py
sparkit/expression/set_operation.py
sparkit_aviad.klein-0.1.0.dist-info/LICENSE
sparkit_aviad.klein-0.1.0.dist-info/METADATA
sparkit_aviad.klein-0.1.0.dist-info/WHEEL
sparkit_aviad.klein-0.1.0.dist-info/top_level.txt
sparkit_aviad.klein-0.1.0.dist-info/RECORD
