Metadata-Version: 2.1
Name: sparkit_aviad.klein
Version: 0.1.0
Summary: A set of utilities and an intuitive API for constructing SQL queries programmatically
Home-page: https://github.com/AviadKlein/sparkit
Author: Aviad Klein
Author-email: Aviad Klein <aviad.klein@gmail.com>
Project-URL: Homepage, https://github.com/AviadKlein/sparkit
Classifier: Programming Language :: Python :: 3
Classifier: License :: OSI Approved :: MIT License
Classifier: Operating System :: OS Independent
Requires-Python: >=3.11
License-File: LICENSE
